<?xml version="1.0" encoding="utf-8" ?>
	<current_observation>
		<credit>Weather Underground Personal Weather Station</credit>
		<credit_URL>http://wunderground.com/weatherstation/</credit_URL>
		<image>
		<url>http://icons.wunderground.com/graphics/bh-wui_logo.gif</url>
		<title>Weather Underground</title>
		<link>http://wunderground.com/weatherstation/</link>
		</image>
		<location>
		<full>Central Saanich, Saanichton, British Columbia</full>
		<neighborhood>Central Saanich</neighborhood>
		<city>Saanichton</city>
		<state>British Columbia</state>
		<zip></zip>
		<latitude>48.591446</latitude>
		<longitude>-123.403488</longitude>
		<elevation>70 ft</elevation>
		</location>
		<station_id>IDNS70</station_id>
		<station_type>WMR968 hybrid</station_type>
		<observation_time>Last Updated on December 4, 3:36 AM PST</observation_time>
		<observation_time_rfc822>Wed, 04 Dec 2013 11:36:54 GMT</observation_time_rfc822>
		<weather></weather>
		<temperature_string>33.6 F (0.9 C)</temperature_string>
		<temp_f>33.6</temp_f>
		<temp_c>0.9</temp_c>
		<relative_humidity>42</relative_humidity>
		<wind_string>From the East at 4.5 MPH Gusting to 8.3 MPH</wind_string>
		<wind_dir>East</wind_dir>
		<wind_degrees>101</wind_degrees>
		<wind_mph>4.5</wind_mph>
		<wind_gust_mph>8.3</wind_gust_mph>
		<pressure_string>30.33" (1027.0 mb)</pressure_string>
		<pressure_mb>1027.0</pressure_mb>
		<pressure_in>30.33</pressure_in>
		<dewpoint_string>12.9 F (-10.6 C)</dewpoint_string>
		<dewpoint_f>12.9</dewpoint_f>
		<dewpoint_c>-10.6</dewpoint_c>
		
		<heat_index_string></heat_index_string>
		<heat_index_f></heat_index_f>
		<heat_index_c></heat_index_c>
		
		
		<windchill_string>29 F (-1 C)</windchill_string>
		<windchill_f>29</windchill_f>
		<windchill_c>-1</windchill_c>
		
		<solar_radiation></solar_radiation>
		<UV></UV>
		<precip_1hr_string>0.00 in (0.0 mm)</precip_1hr_string>
		<precip_1hr_in>0.00</precip_1hr_in>
		<precip_1hr_metric>0.0</precip_1hr_metric>
		<precip_today_string>0.00 in (0.0 cm)</precip_today_string>
		<precip_today_in>0.00</precip_today_in>
		<precip_today_metric>0.0 cm</precip_today_metric>
		<history_url>http://www.wunderground.com/weatherstation/WXDailyHistory.asp?ID=IDNS70</history_url>
		<ob_url>http://www.wunderground.com/cgi-bin/findweather/getForecast?query=48.591446,-123.403488</ob_url>
	</current_observation>

