<?xml version="1.0" encoding="utf-8" ?>
	<current_observation>
		<credit>Weather Underground Personal Weather Station</credit>
		<credit_URL>http://wunderground.com/weatherstation/</credit_URL>
		<image>
		<url>http://icons.wunderground.com/graphics/bh-wui_logo.gif</url>
		<title>Weather Underground</title>
		<link>http://wunderground.com/weatherstation/</link>
		</image>
		<location>
		<full>Millbrook, Cavan-Millbrook-North Monaghan, ON</full>
		<neighborhood>Millbrook</neighborhood>
		<city>Cavan-Millbrook-North Monaghan</city>
		<state>ON</state>
		<zip></zip>
		<latitude>44.150681</latitude>
		<longitude>-78.447876</longitude>
		<elevation>800 ft</elevation>
		</location>
		<station_id>IONCAVAN2</station_id>
		<station_type></station_type>
		<observation_time>Last Updated on December 4, 6:34 AM EST</observation_time>
		<observation_time_rfc822>Wed, 04 Dec 2013 11:34:20 GMT</observation_time_rfc822>
		<weather></weather>
		<temperature_string>28.2 F (-2.1 C)</temperature_string>
		<temp_f>28.2</temp_f>
		<temp_c>-2.1</temp_c>
		<relative_humidity>89</relative_humidity>
		<wind_string>Calm</wind_string>
		<wind_dir>ENE</wind_dir>
		<wind_degrees>59</wind_degrees>
		<wind_mph>0.0</wind_mph>
		<wind_gust_mph>-999.0</wind_gust_mph>
		<pressure_string>29.99" (1015.5 mb)</pressure_string>
		<pressure_mb>1015.5</pressure_mb>
		<pressure_in>29.99</pressure_in>
		<dewpoint_string>25.0 F (-3.9 C)</dewpoint_string>
		<dewpoint_f>25.0</dewpoint_f>
		<dewpoint_c>-3.9</dewpoint_c>
		
		<heat_index_string></heat_index_string>
		<heat_index_f></heat_index_f>
		<heat_index_c></heat_index_c>
		
		
		<windchill_string></windchill_string>
		<windchill_f></windchill_f>
		<windchill_c></windchill_c>
		
		<solar_radiation>0</solar_radiation>
		<UV>0.0</UV>
		<precip_1hr_string>-999.00 in (-2537.5 mm)</precip_1hr_string>
		<precip_1hr_in>-999.00</precip_1hr_in>
		<precip_1hr_metric>-2537.5</precip_1hr_metric>
		<precip_today_string>0.00 in (0.0 cm)</precip_today_string>
		<precip_today_in>0.00</precip_today_in>
		<precip_today_metric>0.0 cm</precip_today_metric>
		<history_url>http://www.wunderground.com/weatherstation/WXDailyHistory.asp?ID=IONCAVAN2</history_url>
		<ob_url>http://www.wunderground.com/cgi-bin/findweather/getForecast?query=44.150681,-78.447876</ob_url>
	</current_observation>

