<?xml version="1.0" encoding="UTF-8"?>
<Ws_Meteo generator="zend" version="1.0"><getRealtimeStationLastData><status>1</status><message>Risultati per la stazione con codice pmn024</message><realtimeDataResponse><station_id>pmn024</station_id><datetime>2013-12-02 14:23:00</datetime><datetime_f>2013-12-02 14:23:00</datetime_f><temperature>8.30</temperature><smlp>1025.8</smlp><rh>42</rh><wind_speed>0.00</wind_speed><wind_direction>177.00</wind_direction><wind_gust>3.10</wind_gust><rain_rate>0.00</rain_rate><daily_rain>0.00</daily_rain><dew_point>-3.90</dew_point><rad></rad><uv></uv><subnet>0</subnet></realtimeDataResponse></getRealtimeStationLastData></Ws_Meteo>
