<?xml version="1.0" encoding="utf-8" ?>
	<current_observation>
		<credit>Weather Underground Personal Weather Station</credit>
		<credit_URL>http://wunderground.com/weatherstation/</credit_URL>
		<image>
		<url>http://icons.wunderground.com/graphics/bh-wui_logo.gif</url>
		<title>Weather Underground</title>
		<link>http://wunderground.com/weatherstation/</link>
		</image>
		<location>
		<full>Viking Stadion, Stavanger, ROGALAND</full>
		<neighborhood>Viking Stadion</neighborhood>
		<city>Stavanger</city>
		<state>ROGALAND</state>
		<zip></zip>
		<latitude>58.928665</latitude>
		<longitude>5.725422</longitude>
		<elevation>300 ft</elevation>
		</location>
		<station_id>IROGALAN12</station_id>
		<station_type>La Crosse, 1Wire</station_type>
		<observation_time>Last Updated on June 18, 2:50 PM CEST</observation_time>
		<observation_time_rfc822>Wed, 18 Jun 2014 12:50:23 GMT</observation_time_rfc822>
		<weather>FEW</weather>
		<temperature_string>66.6 F (19.2 C)</temperature_string>
		<temp_f>66.6</temp_f>
		<temp_c>19.2</temp_c>
		<relative_humidity>44</relative_humidity>
		<wind_string>From the NW at 11.5 MPH Gusting to 11.5 MPH</wind_string>
		<wind_dir>NW</wind_dir>
		<wind_degrees>315</wind_degrees>
		<wind_mph>11.5</wind_mph>
		<wind_gust_mph>11.5</wind_gust_mph>
		<pressure_string>30.11" (1019.5 mb)</pressure_string>
		<pressure_mb>1019.5</pressure_mb>
		<pressure_in>30.11</pressure_in>
		<dewpoint_string>44.0 F (6.7 C)</dewpoint_string>
		<dewpoint_f>44.0</dewpoint_f>
		<dewpoint_c>6.7</dewpoint_c>
		
		<heat_index_string></heat_index_string>
		<heat_index_f></heat_index_f>
		<heat_index_c></heat_index_c>
		
		
		<windchill_string></windchill_string>
		<windchill_f></windchill_f>
		<windchill_c></windchill_c>
		
		<solar_radiation>0</solar_radiation>
		<UV>0.0</UV>
		<precip_1hr_string>0.00 in (0.0 mm)</precip_1hr_string>
		<precip_1hr_in>0.00</precip_1hr_in>
		<precip_1hr_metric>0.0</precip_1hr_metric>
		<precip_today_string>0.00 in (0.0 cm)</precip_today_string>
		<precip_today_in>0.00</precip_today_in>
		<precip_today_metric>0.0 cm</precip_today_metric>
		<history_url>http://www.wunderground.com/weatherstation/WXDailyHistory.asp?ID=IROGALAN12</history_url>
		<ob_url>http://www.wunderground.com/cgi-bin/findweather/getForecast?query=58.928665,5.725422</ob_url>
	</current_observation>

