<?xml version="1.0" encoding="UTF-8"?>
<Ws_Meteo generator="zend" version="1.0"><getRealtimeStationLastData><status>1</status><message>Risultati per la stazione con codice laz013</message><realtimeDataResponse><station_id>laz013</station_id><datetime>2014-06-18 14:39:00</datetime><datetime_utc>2014-06-18 12:39</datetime_utc><temperature>24.60</temperature><smlp>1010.8</smlp><rh>68</rh><wind_speed>6.40</wind_speed><wind_direction>316.00</wind_direction><wind_gust>9.70</wind_gust><rain_rate>0.00</rain_rate><daily_rain>0.20</daily_rain><dew_point>18.30</dew_point><rad></rad><uv></uv></realtimeDataResponse></getRealtimeStationLastData></Ws_Meteo>
