<?xml version="1.0" encoding="UTF-8"?>
<Ws_Meteo generator="zend" version="1.0"><getRealtimeStationLastData><status>1</status><message>Risultati per la stazione con codice pgl090</message><realtimeDataResponse><station_id>pgl090</station_id><datetime>2014-06-18 14:25:00</datetime><datetime_utc>2014-06-18 12:25</datetime_utc><temperature>17.20</temperature><smlp>1012.6</smlp><rh>83</rh><wind_speed>29.00</wind_speed><wind_direction>0.00</wind_direction><wind_gust>48.30</wind_gust><rain_rate>26.70</rain_rate><daily_rain>1.26</daily_rain><dew_point>14.30</dew_point><rad></rad><uv></uv></realtimeDataResponse></getRealtimeStationLastData></Ws_Meteo>
