<?xml version="1.0" encoding="utf-8" ?>
	<current_observation>
		<credit>Weather Underground Personal Weather Station</credit>
		<credit_URL>http://wunderground.com/weatherstation/</credit_URL>
		<image>
		<url>http://icons.wunderground.com/graphics/bh-wui_logo.gif</url>
		<title>Weather Underground</title>
		<link>http://wunderground.com/weatherstation/</link>
		</image>
		<location>
		<full>, Lichtenvoorde, GELDERLAND</full>
		<neighborhood></neighborhood>
		<city>Lichtenvoorde</city>
		<state>GELDERLAND</state>
		<zip></zip>
		<latitude>51.990631</latitude>
		<longitude>6.572697</longitude>
		<elevation>66 ft</elevation>
		</location>
		<station_id>IGELDERL97</station_id>
		<station_type>Alecto WS-4000</station_type>
		<observation_time>Last Updated on June 14, 12:46 PM CEST</observation_time>
		<observation_time_rfc822>Sat, 14 Jun 2014 10:46:20 GMT</observation_time_rfc822>
		<weather></weather>
		<temperature_string>65.5 F (18.6 C)</temperature_string>
		<temp_f>65.5</temp_f>
		<temp_c>18.6</temp_c>
		<relative_humidity>66</relative_humidity>
		<wind_string>Calm</wind_string>
		<wind_dir>ENE</wind_dir>
		<wind_degrees>78</wind_degrees>
		<wind_mph>0.7</wind_mph>
		<wind_gust_mph>4.5</wind_gust_mph>
		<pressure_string>30.07" (1018.2 mb)</pressure_string>
		<pressure_mb>1018.2</pressure_mb>
		<pressure_in>30.07</pressure_in>
		<dewpoint_string>53.8 F (12.1 C)</dewpoint_string>
		<dewpoint_f>53.8</dewpoint_f>
		<dewpoint_c>12.1</dewpoint_c>
		
		<heat_index_string></heat_index_string>
		<heat_index_f></heat_index_f>
		<heat_index_c></heat_index_c>
		
		
		<windchill_string></windchill_string>
		<windchill_f></windchill_f>
		<windchill_c></windchill_c>
		
		<solar_radiation></solar_radiation>
		<UV></UV>
		<precip_1hr_string>0.00 in (0.0 mm)</precip_1hr_string>
		<precip_1hr_in>0.00</precip_1hr_in>
		<precip_1hr_metric>0.0</precip_1hr_metric>
		<precip_today_string>0.00 in (0.0 cm)</precip_today_string>
		<precip_today_in>0.00</precip_today_in>
		<precip_today_metric>0.0 cm</precip_today_metric>
		<history_url>http://www.wunderground.com/weatherstation/WXDailyHistory.asp?ID=IGELDERL97</history_url>
		<ob_url>http://www.wunderground.com/cgi-bin/findweather/getForecast?query=51.990631,6.572697</ob_url>
	</current_observation>

